licencer/__init__.py
licencer/database.py
licencer/errors/exceptions.py
licencer/errors/handlers.py
licencer/errors/schemas.py
licencer/main.py
licencer/questions/__init__.py
licencer/questions/endpoints.py
licencer/questions/models.py
licencer/questions/repositories.py
licencer/questions/schemas.py
licencer/questions/services.py
licencer/sessions/endpoints.py
licencer/sessions/repositories.py
licencer/sessions/schemas.py
licencer/sessions/services.py
licencer/sessions/usos_urls.py
licencer/sessions/verifiers.py
licencer/settings.py
licencer-0.1.0.dist-info/METADATA
licencer-0.1.0.dist-info/WHEEL
licencer-0.1.0.dist-info/RECORD
