Metadata-Version: 2.1
Name: licencer
Version: 0.1.0
Summary: 
Author: Jakub Ostrzołek
Author-email: jakub.ostrzolek.stud@pw.edu.pl
Requires-Python: >=3.10,<4.0
Classifier: Programming Language :: Python :: 3
Classifier: Programming Language :: Python :: 3.10
Classifier: Programming Language :: Python :: 3.11
Requires-Dist: aiosqlite (>=0.17.0,<0.18.0)
Requires-Dist: fastapi (>=0.87.0,<0.88.0)
Requires-Dist: fastapi-sessions (>=0.3.2,<0.4.0)
Requires-Dist: oracledb (>=1.2.1,<2.0.0)
Requires-Dist: python-dotenv (>=0.21.0,<0.22.0)
Requires-Dist: requests-oauthlib (>=1.3.1,<2.0.0)
Requires-Dist: returns (>=0.19.0,<0.20.0)
Requires-Dist: sqlalchemy[asyncio] (>=2.0.0b3,<3.0.0)
Requires-Dist: uvicorn (>=0.20.0,<0.21.0)
